project001/__init__.py
project001/pkg1/__init__.py
project001/pkg1/m1.py
project001-0.2.0.dist-info/WHEEL
project001-0.2.0.dist-info/METADATA
project001-0.2.0.dist-info/RECORD
