Metadata-Version: 2.1
Name: project001
Version: 0.2.0
Summary: project001 is used for simple test
Author: johnypeng
Author-email: 2651903873@qq.com
Requires-Python: >=3.8,<4.0
Classifier: Programming Language :: Python :: 3
Classifier: Programming Language :: Python :: 3.8
Classifier: Programming Language :: Python :: 3.9
Classifier: Programming Language :: Python :: 3.10
Classifier: Programming Language :: Python :: 3.11
Requires-Dist: requests (>=2.32.3,<3.0.0)
